CHANGELOG.md
floodlight/__init__.py
floodlight/core/__init__.py
floodlight/core/code.py
floodlight/core/definitions.py
floodlight/core/events.py
floodlight/core/pitch.py
floodlight/core/property.py
floodlight/core/teamsheet.py
floodlight/core/xy.py
floodlight/io/__init__.py
floodlight/io/datasets.py
floodlight/io/dfl.py
floodlight/io/kinexon.py
floodlight/io/opta.py
floodlight/io/secondspectrum.py
floodlight/io/skillcorner.py
floodlight/io/sportradar.py
floodlight/io/statsbomb.py
floodlight/io/statsperform.py
floodlight/io/tracab.py
floodlight/io/utils.py
floodlight/metrics/__init__.py
floodlight/metrics/entropy.py
floodlight/models/__init__.py
floodlight/models/base.py
floodlight/models/geometry.py
floodlight/models/kinematics.py
floodlight/models/kinetics.py
floodlight/models/space.py
floodlight/settings.py
floodlight/transforms/__init__.py
floodlight/transforms/filter.py
floodlight/utils/__init__.py
floodlight/utils/types.py
floodlight/vis/__init__.py
floodlight/vis/pitches.py
floodlight/vis/positions.py
floodlight/vis/utils.py
LICENSE
floodlight-1.1.0.dist-info/LICENSE
floodlight-1.1.0.dist-info/METADATA
floodlight-1.1.0.dist-info/WHEEL
floodlight-1.1.0.dist-info/RECORD
