Metadata-Version: 2.1
Name: floodlight
Version: 1.1.0
Summary: A high-level framework for sports data analysis
Home-page: https://github.com/floodlight-sports/floodlight
License: MIT
Keywords: sports analytics,sports data analysis,tracking data
Author: draabe
Author-email: draabx@posteo.org
Requires-Python: >=3.10,<3.13
Classifier: Environment :: Console
Classifier: License :: OSI Approved :: MIT License
Classifier: Operating System :: Microsoft :: Windows
Classifier: Operating System :: Unix
Classifier: Programming Language :: Python :: 3
Classifier: Programming Language :: Python :: 3.10
Classifier: Programming Language :: Python :: 3.11
Classifier: Programming Language :: Python :: 3.12
Requires-Dist: h5py (>=3.11.0,<4.0.0)
Requires-Dist: iso8601 (>=2.1.0,<3.0.0)
Requires-Dist: lxml (>=5.3.0,<6.0.0)
Requires-Dist: matplotlib (>=3.9.2,<4.0.0)
Requires-Dist: numpy (>=2.1.1,<3.0.0)
Requires-Dist: pandas (>=2.2.2,<3.0.0)
Requires-Dist: pytz (>=2024.1,<2025.0)
Requires-Dist: scipy (>=1.14.1,<2.0.0)
Project-URL: Documentation, https://floodlight.readthedocs.io/en/latest/
Project-URL: Repository, https://github.com/floodlight-sports/floodlight
